krl_geospatial/__init__.py
krl_geospatial/__version__.py
krl_geospatial/analysis/__init__.py
krl_geospatial/analysis/hotspot.py
krl_geospatial/analysis/pattern.py
krl_geospatial/clustering/__init__.py
krl_geospatial/clustering/dbscan.py
krl_geospatial/clustering/maxp.py
krl_geospatial/clustering/metrics.py
krl_geospatial/clustering/redcap.py
krl_geospatial/clustering/skater.py
krl_geospatial/core/__init__.py
krl_geospatial/core/base.py
krl_geospatial/econometrics/__init__.py
krl_geospatial/econometrics/_fix_spatial_models.py
krl_geospatial/econometrics/autocorrelation.py
krl_geospatial/econometrics/base.py
krl_geospatial/econometrics/diagnostics.py
krl_geospatial/econometrics/error_model.py
krl_geospatial/econometrics/gwr.py
krl_geospatial/econometrics/lag_model.py
krl_geospatial/econometrics/model_selection.py
krl_geospatial/econometrics/ols.py
krl_geospatial/econometrics/parallel_gwr.py
krl_geospatial/econometrics/spatial_models.py
krl_geospatial/indexing/__init__.py
krl_geospatial/indexing/accelerated_weights.py
krl_geospatial/indexing/bulk_operations.py
krl_geospatial/indexing/grid_index.py
krl_geospatial/indexing/rtree_index.py
krl_geospatial/indexing/spatial_index.py
krl_geospatial/interpolation/__init__.py
krl_geospatial/interpolation/idw.py
krl_geospatial/interpolation/kriging.py
krl_geospatial/interpolation/splines.py
krl_geospatial/io/__init__.py
krl_geospatial/io/readers.py
krl_geospatial/io/writers.py
krl_geospatial/mapping/__init__.py
krl_geospatial/mapping/bubble.py
krl_geospatial/mapping/choropleth.py
krl_geospatial/mapping/export.py
krl_geospatial/mapping/flow.py
krl_geospatial/mapping/heatmap.py
krl_geospatial/mapping/interactive.py
krl_geospatial/mapping/static.py
krl_geospatial/mapping/utils.py
krl_geospatial/network/__init__.py
krl_geospatial/network/community.py
krl_geospatial/network/routing.py
krl_geospatial/network/topology.py
krl_geospatial/weights/__init__.py
krl_geospatial/weights/base.py
krl_geospatial/weights/contiguity.py
krl_geospatial_tools-0.2.0.dist-info/licenses/LICENSE
krl_geospatial_tools-0.2.0.dist-info/METADATA
krl_geospatial_tools-0.2.0.dist-info/WHEEL
krl_geospatial_tools-0.2.0.dist-info/entry_points.txt
krl_geospatial_tools-0.2.0.dist-info/top_level.txt
krl_geospatial_tools-0.2.0.dist-info/RECORD
