Metadata-Version: 2.4
Name: krl-geospatial-tools
Version: 0.2.0
Summary: Geospatial analysis and mapping tools for the Khipu Intelligence Suite
Author-email: KR-Labs Foundation <dev@krlabs.org>
Maintainer-email: KR-Labs Foundation <support@krlabs.dev>
License: Apache-2.0
Project-URL: Homepage, https://krlabs.dev
Project-URL: Documentation, https://docs.krlabs.dev/geospatial-tools
Project-URL: Repository, https://github.com/kr-labs/krl-geospatial-tools
Project-URL: Changelog, https://github.com/kr-labs/krl-geospatial-tools/blob/main/CHANGELOG.md
Classifier: Development Status :: 3 - Alpha
Classifier: Intended Audience :: Science/Research
Classifier: License :: OSI Approved :: Apache Software License
Classifier: Programming Language :: Python :: 3
Classifier: Programming Language :: Python :: 3.11
Requires-Python: >=3.11
License-File: LICENSE
Requires-Dist: geopandas>=0.13.0
Requires-Dist: shapely>=2.0.0
Requires-Dist: folium>=0.14.0
Requires-Dist: plotly>=5.17.0
Requires-Dist: pandas>=2.1.0
Requires-Dist: numpy>=1.26.0
Requires-Dist: krl-open-core>=0.2.0
Requires-Dist: krl-types~=0.2.0
Provides-Extra: dev
Requires-Dist: black>=23.0.0; extra == "dev"
Requires-Dist: isort>=5.12.0; extra == "dev"
Requires-Dist: flake8>=6.0.0; extra == "dev"
Requires-Dist: mypy>=1.5.0; extra == "dev"
Provides-Extra: test
Requires-Dist: pytest>=7.4.0; extra == "test"
Requires-Dist: pytest-cov>=4.1.0; extra == "test"
Requires-Dist: pytest-mock>=3.11.0; extra == "test"
Provides-Extra: spatial
Requires-Dist: pysal>=23.0; extra == "spatial"
Requires-Dist: rtree>=1.0.0; extra == "spatial"
Requires-Dist: scikit-learn>=1.2.0; extra == "spatial"
Provides-Extra: geocoding
Requires-Dist: geopy>=2.3.0; extra == "geocoding"
Requires-Dist: googlemaps>=4.10.0; extra == "geocoding"
Dynamic: license-file
